llm_swarm/__init__.py
llm_swarm/__main__.py
llm_swarm-0.1.1.dist-info/LICENSE
llm_swarm-0.1.1.dist-info/METADATA
llm_swarm-0.1.1.dist-info/WHEEL
llm_swarm-0.1.1.dist-info/RECORD
