Metadata-Version: 2.1
Name: llm-swarm
Version: 0.1.1
Summary: 
Author: Guilherme Penedo
Author-email: guilherme@huggingface.co
Requires-Python: >=3.9,<3.13
Classifier: Programming Language :: Python :: 3
Classifier: Programming Language :: Python :: 3.9
Classifier: Programming Language :: Python :: 3.10
Classifier: Programming Language :: Python :: 3.11
Classifier: Programming Language :: Python :: 3.12
Requires-Dist: aiohttp (>=3.8.6,<4.0.0)
Requires-Dist: asyncio (>=3.4.3,<4.0.0)
Requires-Dist: datasets (>=2.16.1,<3.0.0)
Requires-Dist: hf-transfer (>=0.1.4,<0.2.0)
Requires-Dist: huggingface-hub (>=0.20.3,<0.21.0)
Requires-Dist: jinja2 (>=3.1.2,<4.0.0)
Requires-Dist: pandas (>=2.1.2,<3.0.0)
Requires-Dist: tqdm (>=4.66.1,<5.0.0)
Requires-Dist: transformers (>=4.36.2,<5.0.0)
Requires-Dist: tyro (>=0.5.12,<0.6.0)
Requires-Dist: wonderwords (>=2.2.0,<3.0.0)
